hwc/__init__.py
hwc/_version.py
hwc/avt_5710/__init__.py
hwc/common/__init__.py
hwc/common/_base.py
hwc/manson/__init__.py
hwc/waveshare/__init__.py
hwc-0.2.1.dist-info/licenses/LICENSE
hwc-0.2.1.dist-info/METADATA
hwc-0.2.1.dist-info/WHEEL
hwc-0.2.1.dist-info/top_level.txt
hwc-0.2.1.dist-info/RECORD
