Metadata-Version: 2.4
Name: hwc
Version: 0.2.1
Summary: High level interfaces and implementations to simplify communication with IO devices.
Maintainer-email: Piotr Sznapka <piotr.sznapka@int2code.com>, Marcin Tomiczek <marcin.tomiczek@int2code.com>
License: MIT License
Requires-Python: >=3.11
License-File: LICENSE
Requires-Dist: pymodbus==3.9.2
Requires-Dist: pyserial
Requires-Dist: retry
Provides-Extra: test
Requires-Dist: coverage; extra == "test"
Requires-Dist: pytest; extra == "test"
Requires-Dist: pytest-cov; extra == "test"
Requires-Dist: pytest-html; extra == "test"
Provides-Extra: dev
Requires-Dist: coverage; extra == "dev"
Requires-Dist: pytest; extra == "dev"
Requires-Dist: pytest-cov; extra == "dev"
Requires-Dist: pytest-html; extra == "dev"
Requires-Dist: black; extra == "dev"
Requires-Dist: pylint; extra == "dev"
Requires-Dist: tox; extra == "dev"
Provides-Extra: docs
Requires-Dist: coverage; extra == "docs"
Requires-Dist: pytest; extra == "docs"
Requires-Dist: pytest-cov; extra == "docs"
Requires-Dist: pytest-html; extra == "docs"
Requires-Dist: sphinx; extra == "docs"
Requires-Dist: sphinx-rtd-theme; extra == "docs"
Requires-Dist: sphinxcontrib-programoutput; extra == "docs"
Requires-Dist: myst-parser; extra == "docs"
Dynamic: license-file
